vr/__init__.py
vr/events/__init__.py
vr/events/tests/__init__.py
vr/events/tests/test_listener.py
vr.events-2.0.0.dist-info/LICENSE
vr.events-2.0.0.dist-info/METADATA
vr.events-2.0.0.dist-info/WHEEL
vr.events-2.0.0.dist-info/top_level.txt
vr.events-2.0.0.dist-info/RECORD
